redash_query_download/__init__.py
redash_query_download/clidriver.py
redash_query_download-0.0.9.data/scripts/rqd
redash_query_download-0.0.9.dist-info/LICENSE
redash_query_download-0.0.9.dist-info/METADATA
redash_query_download-0.0.9.dist-info/WHEEL
redash_query_download-0.0.9.dist-info/top_level.txt
redash_query_download-0.0.9.dist-info/RECORD
