Metadata-Version: 2.1
Name: redash-query-download
Version: 0.0.9
Summary: redash query download client
Home-page: https://github.com/shigemk2/redash_query_download
Author: Michihito Shigemura
Author-email: i.am.shige@gmail.com
License: UNKNOWN
Platform: UNKNOWN
Classifier: Programming Language :: Python :: 3
Classifier: License :: OSI Approved :: MIT License
Classifier: Operating System :: OS Independent
